getref/__init__.py
getref/cli.py
getref-0.35.data/scripts/getref
getref-0.35.dist-info/LICENSE
getref-0.35.dist-info/METADATA
getref-0.35.dist-info/WHEEL
getref-0.35.dist-info/top_level.txt
getref-0.35.dist-info/RECORD
