Metadata-Version: 2.1
Name: getref
Version: 0.35
Summary: Command line interface to dblp
Home-page: https://github.com/martisak/getref
Author: Martin Isaksson
Author-email: martin.isaksson@gmail.com
License: MIT
Keywords: bibtex dblp
Platform: any
Classifier: Development Status :: 3 - Alpha
Classifier: License :: OSI Approved :: MIT License
Classifier: Programming Language :: Python :: 3.9
Classifier: Intended Audience :: Science/Research
Classifier: Topic :: Scientific/Engineering
Classifier: Environment :: Console
Requires-Dist: simple-term-menu (==0.10.5)
Requires-Dist: Pygments (==2.8.1)
Requires-Dist: requests (==2.25.1)
Requires-Dist: multiprocess (==0.70.11.1)
